easypost_core/__init__.py
easypost_core/__version__.py
easypost_core/requirements.txt
easypost_core/logging/__init__.py
easypost_core/logging/elasticsearch/__init__.py
easypost_core/logging/elasticsearch/elasticsearch_logger.py
easypost_core/logging/elasticsearch/utilities.py
easypost_core/mailing/__init__.py
easypost_core/mailing/email_sender.py
easypost_core/slack/__init__.py
easypost_core/slack/slack_client.py
easypost_core/sql_server/__init__.py
easypost_core/sql_server/sql_server_database.py
easypost_core-1.0.10.dist-info/METADATA
easypost_core-1.0.10.dist-info/WHEEL
easypost_core-1.0.10.dist-info/licenses/LICENSE
easypost_core-1.0.10.dist-info/RECORD
