Metadata-Version: 2.3
Name: easypost-core
Version: 1.0.10
Summary: A package providing easy-to-use solutions for common recurring problems. More info in the README file
Project-URL: Homepage, https://bitbucket.org/easypostit/easypost-core
Author-email: Postalia Belgium <it@easypost.eu>
License-Expression: MIT
License-File: LICENSE
Classifier: License :: OSI Approved :: MIT License
Classifier: Operating System :: OS Independent
Classifier: Programming Language :: Python :: 3
Requires-Python: >=3.8
Requires-Dist: elasticsearch~=8.14.0
Requires-Dist: pyodbc~=5.1.0
Requires-Dist: slack-sdk~=3.30.0
